scoda/__init__.py
scoda/config/default_settings.json
scoda/elements/bar.py
scoda/elements/composition.py
scoda/elements/message.py
scoda/elements/track.py
scoda/enumerations/message_type.py
scoda/enumerations/tokenisation_flags.py
scoda/enumerations/tokenisation_prefixes.py
scoda/enumerations/tokeniser_type.py
scoda/exceptions/bar_exception.py
scoda/exceptions/composition_exception.py
scoda/exceptions/sequence_exception.py
scoda/exceptions/tokenisation_exception.py
scoda/exceptions/track_exception.py
scoda/midi/midi_file.py
scoda/midi/midi_message.py
scoda/midi/midi_track.py
scoda/misc/decorators.py
scoda/misc/music_theory.py
scoda/misc/scoda_logging.py
scoda/misc/util.py
scoda/sequences/absolute_sequence.py
scoda/sequences/abstract_sequence.py
scoda/sequences/relative_sequence.py
scoda/sequences/sequence.py
scoda/settings/settings.py
scoda/tokenisation/notelike_tokenisation.py
scoda-2.5.dist-info/licenses/LICENSE.md
scoda-2.5.dist-info/METADATA
scoda-2.5.dist-info/WHEEL
scoda-2.5.dist-info/top_level.txt
scoda-2.5.dist-info/RECORD
