Metadata-Version: 2.4
Name: scoda
Version: 2.5
Summary: A MIDI and music data manipulation library
Author-email: Felix Schön <schoen@kr.tuwien.ac.at>
License: MIT License
Project-URL: Homepage, https://github.com/FelixSchoen/S-Coda
Project-URL: Bugtracker, https://github.com/FelixSchoen/S-Coda/issues
Keywords: midi,music
Requires-Python: >=3.11
License-File: LICENSE.md
Requires-Dist: mido
Requires-Dist: numpy
Requires-Dist: matplotlib
Provides-Extra: test
Requires-Dist: pytest; extra == "test"
Requires-Dist: pytest-xdist; extra == "test"
Requires-Dist: pytest-cov; extra == "test"
Requires-Dist: coverage; extra == "test"
Requires-Dist: build; extra == "test"
Provides-Extra: deploy
Requires-Dist: build; extra == "deploy"
Requires-Dist: twine; extra == "deploy"
Requires-Dist: pdoc3; extra == "deploy"
Dynamic: license-file
